LICENSE.txt
MANIFEST.in
README.md
setup.py
PyEng/Grammar.py
PyEng/Words.py
PyEng/__init__.py
PyEng.egg-info/PKG-INFO
PyEng.egg-info/SOURCES.txt
PyEng.egg-info/dependency_links.txt
PyEng.egg-info/top_level.txt
PyEng/data/dictionary.json