Metadata-Version: 2.1
Name: PyEng
Version: 1.0.4
Summary: PyEng is a general-purpose Python package that contains functions related to the English language.
Home-page: https://github.com/Anikethc/PyEng
Download-URL: https://pypi.org/project/PyEng
Author: Aniketh Chavare
Author-email: anikethchavare@outlook.com
License: MIT
Keywords: English
License-File: LICENSE.txt
